mp3cloud/__init__.py
mp3cloud/__main__.py
mp3cloud/api.py
mp3cloud/objects.py
mp3cloud/scripts/search.sh
mp3cloud/scripts/token.sh
mp3cloud/utils.py
mp3cloud-0.1.1.dist-info/LICENSE
mp3cloud-0.1.1.dist-info/METADATA
mp3cloud-0.1.1.dist-info/WHEEL
mp3cloud-0.1.1.dist-info/RECORD
