Metadata-Version: 2.1
Name: mp3cloud
Version: 0.1.1
Summary: Search and download any music from freemp3cloud.com
Home-page: https://github.com/rtcq/freemp3cloud-downloader
License: MIT
Author: Momo
Author-email: lo3me@proton.me
Requires-Python: >=3.8,<4.0
Classifier: License :: OSI Approved :: MIT License
Classifier: Programming Language :: Python :: 3
Classifier: Programming Language :: Python :: 3.8
Classifier: Programming Language :: Python :: 3.9
Classifier: Programming Language :: Python :: 3.10
Classifier: Programming Language :: Python :: 3.11
Requires-Dist: bs4 (>=0.0.1,<0.0.2)
Requires-Dist: requests (>=2.28.1,<3.0.0)
Requires-Dist: rich (>=12.6.0,<13.0.0)
Project-URL: Bug Tracker, https://github.com/rtcq/freemp3cloud-downloader/issues
Project-URL: Repository, https://github.com/rtcq/freemp3cloud-downloader
